README.md
easy_readme/__init__.py
easy_readme/answers_to_markdown.py
easy_readme/command_line.py
easy_readme/defaults.py
easy_readme/setup.py
easy_readme.egg-info/PKG-INFO
easy_readme.egg-info/SOURCES.txt
easy_readme.egg-info/dependency_links.txt
easy_readme.egg-info/entry_points.txt
easy_readme.egg-info/not-zip-safe
easy_readme.egg-info/requires.txt
easy_readme.egg-info/top_level.txt