Metadata-Version: 1.0
Name: easy-readme
Version: 0.2.0
Summary: Generate a barebones readme based off of your directory
Home-page: http://github.com/mcabrams/easy_readme
Author: Matthew Carlos Abrams
Author-email: UNKNOWN
License: MIT
Platform: UNKNOWN
